satellite_populate/__init__.py
satellite_populate/api.py
satellite_populate/assertion_operators.py
satellite_populate/base.py
satellite_populate/cli.py
satellite_populate/commands.py
satellite_populate/constants.py
satellite_populate/decorators.py
satellite_populate/main.py
satellite_populate/utils.py
satellite_populate-0.1.3.dist-info/DESCRIPTION.rst
satellite_populate-0.1.3.dist-info/METADATA
satellite_populate-0.1.3.dist-info/RECORD
satellite_populate-0.1.3.dist-info/WHEEL
satellite_populate-0.1.3.dist-info/entry_points.txt
satellite_populate-0.1.3.dist-info/metadata.json
satellite_populate-0.1.3.dist-info/top_level.txt
