Metadata-Version: 2.0
Name: satellite-populate
Version: 0.1.3
Summary: Populate and Validate the System using YAML
Home-page: https://github.com/SatelliteQE/satellite-populate
Author: Bruno Rocha
Author-email: rochacbruno@gmail.com
License: GNU General Public License v3
Keywords: satellite_populate
Platform: UNKNOWN
Classifier: Development Status :: 2 - Pre-Alpha
Classifier: Intended Audience :: Developers
Classifier: License :: OSI Approved :: GNU General Public License v3 (GPLv3)
Classifier: Natural Language :: English
Classifier: Programming Language :: Python :: 2
Classifier: Programming Language :: Python :: 2.6
Classifier: Programming Language :: Python :: 2.7
Classifier: Programming Language :: Python :: 3
Classifier: Programming Language :: Python :: 3.3
Classifier: Programming Language :: Python :: 3.4
Classifier: Programming Language :: Python :: 3.5
Requires-Dist: Click (>=6.0)
Requires-Dist: PyYAML
Requires-Dist: coloredlogs
Requires-Dist: import-string
Requires-Dist: jinja2
Requires-Dist: six
